[
  {
    "Title": "Song_MadWorld_BH_87bpm_100deg",
    "OverallAccuracy": 0.988390267,
    "NoteOnAccuracy": 1.0,
    "FrameFractionAccuracy": 0.9876589,
    "LeftHandPersistence": 1.0,
    "RightHandPersistence": 1.0,
    "RecognizeToPressTimeLeftHand": 1.889493,
    "RecognizeToPressTimeRightHand": 1.822827,
    "LeftThumbAccuracy": 0.9884282,
    "LeftIndexAccuracy": 0.978494644,
    "LeftMiddleAccuracy": 0.986792445,
    "LeftRingAccuracy": 0.99473685,
    "LeftPinkyAccuracy": 0.9875862,
    "RightThumbAccuracy": 0.990881443,
    "RightIndexAccuracy": 0.9953271,
    "RightMiddleAccuracy": 1.0,
    "RightRingAccuracy": 0.9777778,
    "RightPinkyAccuracy": 0.9889706,
    "OctaveLeftAccuracy": -1.0,
    "OctaveMiddleLeftAccuracy": 0.986707,
    "OctaveMiddleRightAccuracy": 0.989420056,
    "OctaveRightAccuracy": 0.9889706,
    "FingerWidthMultiplier": 1.0,
    "TopMask": 0.0,
    "BottomMask": 0.0,
    "LeftMask": 0.0,
    "RightMask": 0.0,
    "LightingAverage": 0.06535372,
    "LightingContrast": 0.019715663,
    "LightingScore": 0.9987114,
    "WorstFrameAccuracyScore": 0.981570363,
    "WorstFrameAccuracyStart": 3.7,
    "WorstFrameAccuracyEnd": 24.8000011,
    "WorstFrameAccuracyDuration": 21.1,
    "CameraFPS": 89.9681,
    "UnityFPS": 60.0254745,
    "TestAppVersion": "0.2",
    "TrackingServiceVersion": "5.17.1",
    "TrackingModelVersion": "N/A",
    "InitThreshold": -1.0,
    "KillThreshold": -1.0,
    "TrackingProviderName": "Screentop Service Provider",
    "TrackingUsesInterpolation": false,
    "TestedAt": "20231214_125248"
  },
  {
    "Title": "Song_MadWorld_BH_87bpm_105deg",
    "OverallAccuracy": 0.993361,
    "NoteOnAccuracy": 1.0,
    "FrameFractionAccuracy": 0.9933531,
    "LeftHandPersistence": 1.0,
    "RightHandPersistence": 1.0,
    "RecognizeToPressTimeLeftHand": 1.744578,
    "RecognizeToPressTimeRightHand": 1.7668,
    "LeftThumbAccuracy": 0.9926403,
    "LeftIndexAccuracy": 0.9817708,
    "LeftMiddleAccuracy": 0.998168468,
    "LeftRingAccuracy": 1.0,
    "LeftPinkyAccuracy": 0.9885787,
    "RightThumbAccuracy": 0.9916434,
    "RightIndexAccuracy": 0.996078432,
    "RightMiddleAccuracy": 1.0,
    "RightRingAccuracy": 1.0,
    "RightPinkyAccuracy": 0.990415335,
    "OctaveLeftAccuracy": -1.0,
    "OctaveMiddleLeftAccuracy": 0.990257859,
    "OctaveMiddleRightAccuracy": 0.9956553,
    "OctaveRightAccuracy": 0.990415335,
    "FingerWidthMultiplier": 1.0,
    "TopMask": 0.39,
    "BottomMask": 0.2,
    "LeftMask": 0.2,
    "RightMask": 0.2,
    "LightingAverage": 0.0609485544,
    "LightingContrast": 0.0192159042,
    "LightingScore": 0.9988287,
    "WorstFrameAccuracyScore": 0.869047642,
    "WorstFrameAccuracyStart": 32.2,
    "WorstFrameAccuracyEnd": 32.8,
    "WorstFrameAccuracyDuration": 0.6,
    "CameraFPS": 89.97195,
    "UnityFPS": 60.00658,
    "TestAppVersion": "0.2",
    "TrackingServiceVersion": "5.17.1",
    "TrackingModelVersion": "N/A",
    "InitThreshold": -1.0,
    "KillThreshold": -1.0,
    "TrackingProviderName": "Screentop Service Provider",
    "TrackingUsesInterpolation": false,
    "TestedAt": "20231214_125341"
  },
  {
    "Title": "Song_MadWorld_BH_87bpm_90deg",
    "OverallAccuracy": 0.980448067,
    "NoteOnAccuracy": 0.983871,
    "FrameFractionAccuracy": 0.982431352,
    "LeftHandPersistence": 1.0,
    "RightHandPersistence": 1.0,
    "RecognizeToPressTimeLeftHand": 1.022212,
    "RecognizeToPressTimeRightHand": 1.033323,
    "LeftThumbAccuracy": 0.999082565,
    "LeftIndexAccuracy": 0.9840849,
    "LeftMiddleAccuracy": 0.981412649,
    "LeftRingAccuracy": 1.0,
    "LeftPinkyAccuracy": 0.979354858,
    "RightThumbAccuracy": 0.9925187,
    "RightIndexAccuracy": 0.9163763,
    "RightMiddleAccuracy": 1.0,
    "RightRingAccuracy": 0.9359268,
    "RightPinkyAccuracy": 0.975308657,
    "OctaveLeftAccuracy": -1.0,
    "OctaveMiddleLeftAccuracy": 0.981955767,
    "OctaveMiddleRightAccuracy": 0.980125546,
    "OctaveRightAccuracy": 0.975308657,
    "FingerWidthMultiplier": 1.0,
    "TopMask": 0.39,
    "BottomMask": 0.2,
    "LeftMask": 0.2,
    "RightMask": 0.2,
    "LightingAverage": 0.03180746,
    "LightingContrast": 0.008156037,
    "LightingScore": 0.999723434,
    "WorstFrameAccuracyScore": 0.8756165,
    "WorstFrameAccuracyStart": 1.2,
    "WorstFrameAccuracyEnd": 4.0,
    "WorstFrameAccuracyDuration": 2.8,
    "CameraFPS": 90.00246,
    "UnityFPS": 60.0025444,
    "TestAppVersion": "0.2",
    "TrackingServiceVersion": "5.17.1",
    "TrackingModelVersion": "N/A",
    "InitThreshold": -1.0,
    "KillThreshold": -1.0,
    "TrackingProviderName": "Screentop Service Provider",
    "TrackingUsesInterpolation": false,
    "TestedAt": "20231214_125434"
  },
  {
    "Title": "Song_MadWorld_BH_87bpm_95deg",
    "OverallAccuracy": 0.9912372,
    "NoteOnAccuracy": 1.0,
    "FrameFractionAccuracy": 0.9902431,
    "LeftHandPersistence": 1.0,
    "RightHandPersistence": 1.0,
    "RecognizeToPressTimeLeftHand": 2.47775,
    "RecognizeToPressTimeRightHand": 2.47775,
    "LeftThumbAccuracy": 0.9866794,
    "LeftIndexAccuracy": 0.9919571,
    "LeftMiddleAccuracy": 0.978378356,
    "LeftRingAccuracy": 1.0,
    "LeftPinkyAccuracy": 0.9895288,
    "RightThumbAccuracy": 0.9947781,
    "RightIndexAccuracy": 1.0,
    "RightMiddleAccuracy": 0.9979253,
    "RightRingAccuracy": 0.9974874,
    "RightPinkyAccuracy": 0.9967213,
    "OctaveLeftAccuracy": -1.0,
    "OctaveMiddleLeftAccuracy": 0.9878261,
    "OctaveMiddleRightAccuracy": 0.9927615,
    "OctaveRightAccuracy": 0.9967213,
    "FingerWidthMultiplier": 1.0,
    "TopMask": 0.39,
    "BottomMask": 0.2,
    "LeftMask": 0.2,
    "RightMask": 0.2,
    "LightingAverage": 0.0646984056,
    "LightingContrast": 0.0196831524,
    "LightingScore": 0.998690248,
    "WorstFrameAccuracyScore": 0.888322,
    "WorstFrameAccuracyStart": 13.3,
    "WorstFrameAccuracyEnd": 14.7,
    "WorstFrameAccuracyDuration": 1.4,
    "CameraFPS": 89.99734,
    "UnityFPS": 60.04428,
    "TestAppVersion": "0.2",
    "TrackingServiceVersion": "5.17.1",
    "TrackingModelVersion": "N/A",
    "InitThreshold": -1.0,
    "KillThreshold": -1.0,
    "TrackingProviderName": "Screentop Service Provider",
    "TrackingUsesInterpolation": false,
    "TestedAt": "20231214_125528"
  }
]
