[
  {
    "Title": "Song_AmazingGrace_BH_100bpm_100deg",
    "OverallAccuracy": 0.9637718,
    "NoteOnAccuracy": 0.9866667,
    "FrameFractionAccuracy": 0.964561,
    "LeftHandPersistence": 1.0,
    "RightHandPersistence": 1.0,
    "RecognizeToPressTimeLeftHand": 3.767401,
    "RecognizeToPressTimeRightHand": 3.100741,
    "LeftThumbAccuracy": 0.9302072,
    "LeftIndexAccuracy": 1.0,
    "LeftMiddleAccuracy": 1.0,
    "LeftRingAccuracy": 0.7185185,
    "LeftPinkyAccuracy": 0.962963,
    "RightThumbAccuracy": 0.9942748,
    "RightIndexAccuracy": 1.0,
    "RightMiddleAccuracy": 0.997528851,
    "RightRingAccuracy": 0.9948454,
    "RightPinkyAccuracy": 0.988778055,
    "OctaveLeftAccuracy": -1.0,
    "OctaveMiddleLeftAccuracy": 0.9310215,
    "OctaveMiddleRightAccuracy": 0.9894951,
    "OctaveRightAccuracy": 1.0,
    "FingerWidthMultiplier": 1.0,
    "TopMask": 0.0,
    "BottomMask": 0.0,
    "LeftMask": 0.0,
    "RightMask": 0.0,
    "LightingAverage": 0.06720206,
    "LightingContrast": 0.0199343041,
    "LightingScore": 0.9986602,
    "WorstFrameAccuracyScore": 0.922639966,
    "WorstFrameAccuracyStart": 12.4000006,
    "WorstFrameAccuracyEnd": 21.9,
    "WorstFrameAccuracyDuration": 9.5,
    "CameraFPS": 89.9742,
    "UnityFPS": 59.9758339,
    "TestAppVersion": "0.2",
    "TrackingServiceVersion": "5.17.1",
    "TrackingModelVersion": "N/A",
    "InitThreshold": -1.0,
    "KillThreshold": -1.0,
    "TrackingProviderName": "Screentop Service Provider",
    "TrackingUsesInterpolation": false,
    "TestedAt": "20231214_121844"
  },
  {
    "Title": "Song_AmazingGrace_BH_100bpm_105deg",
    "OverallAccuracy": 0.931859732,
    "NoteOnAccuracy": 0.9350649,
    "FrameFractionAccuracy": 0.943768859,
    "LeftHandPersistence": 1.0,
    "RightHandPersistence": 1.0,
    "RecognizeToPressTimeLeftHand": 3.811486,
    "RecognizeToPressTimeRightHand": 3.200246,
    "LeftThumbAccuracy": 0.995584965,
    "LeftIndexAccuracy": 0.906122446,
    "LeftMiddleAccuracy": 1.0,
    "LeftRingAccuracy": 0.8866995,
    "LeftPinkyAccuracy": 0.9203704,
    "RightThumbAccuracy": 0.9920477,
    "RightIndexAccuracy": 0.590909064,
    "RightMiddleAccuracy": 0.997545,
    "RightRingAccuracy": 0.565891445,
    "RightPinkyAccuracy": 0.9910828,
    "OctaveLeftAccuracy": -1.0,
    "OctaveMiddleLeftAccuracy": 0.9328712,
    "OctaveMiddleRightAccuracy": 0.9239825,
    "OctaveRightAccuracy": 1.0,
    "FingerWidthMultiplier": 1.0,
    "TopMask": 0.39,
    "BottomMask": 0.2,
    "LeftMask": 0.2,
    "RightMask": 0.2,
    "LightingAverage": 0.0619014278,
    "LightingContrast": 0.0192189217,
    "LightingScore": 0.998810232,
    "WorstFrameAccuracyScore": 0.8782061,
    "WorstFrameAccuracyStart": 35.6000023,
    "WorstFrameAccuracyEnd": 43.8,
    "WorstFrameAccuracyDuration": 8.2,
    "CameraFPS": 89.9738,
    "UnityFPS": 60.0079231,
    "TestAppVersion": "0.2",
    "TrackingServiceVersion": "5.17.1",
    "TrackingModelVersion": "N/A",
    "InitThreshold": -1.0,
    "KillThreshold": -1.0,
    "TrackingProviderName": "Screentop Service Provider",
    "TrackingUsesInterpolation": false,
    "TestedAt": "20231214_121940"
  },
  {
    "Title": "Song_AmazingGrace_BH_100bpm_90deg",
    "OverallAccuracy": 0.970090568,
    "NoteOnAccuracy": 0.9866667,
    "FrameFractionAccuracy": 0.9662789,
    "LeftHandPersistence": 1.0,
    "RightHandPersistence": 1.0,
    "RecognizeToPressTimeLeftHand": 3.199968,
    "RecognizeToPressTimeRightHand": 2.544419,
    "LeftThumbAccuracy": 0.9978881,
    "LeftIndexAccuracy": 1.0,
    "LeftMiddleAccuracy": 1.0,
    "LeftRingAccuracy": 0.7821782,
    "LeftPinkyAccuracy": 0.963964,
    "RightThumbAccuracy": 0.9217221,
    "RightIndexAccuracy": 0.9956522,
    "RightMiddleAccuracy": 0.998330534,
    "RightRingAccuracy": 0.9100529,
    "RightPinkyAccuracy": 0.9937107,
    "OctaveLeftAccuracy": -1.0,
    "OctaveMiddleLeftAccuracy": 0.9585843,
    "OctaveMiddleRightAccuracy": 0.977500856,
    "OctaveRightAccuracy": 1.0,
    "FingerWidthMultiplier": 1.0,
    "TopMask": 0.39,
    "BottomMask": 0.2,
    "LeftMask": 0.2,
    "RightMask": 0.2,
    "LightingAverage": 0.07169375,
    "LightingContrast": 0.0211777445,
    "LightingScore": 0.9984781,
    "WorstFrameAccuracyScore": 0.664966,
    "WorstFrameAccuracyStart": 11.8,
    "WorstFrameAccuracyEnd": 13.2,
    "WorstFrameAccuracyDuration": 1.4,
    "CameraFPS": 89.97133,
    "UnityFPS": 60.0122337,
    "TestAppVersion": "0.2",
    "TrackingServiceVersion": "5.17.1",
    "TrackingModelVersion": "N/A",
    "InitThreshold": -1.0,
    "KillThreshold": -1.0,
    "TrackingProviderName": "Screentop Service Provider",
    "TrackingUsesInterpolation": false,
    "TestedAt": "20231214_122036"
  },
  {
    "Title": "Song_AmazingGrace_BH_100bpm_95deg",
    "OverallAccuracy": 0.966627359,
    "NoteOnAccuracy": 0.9868421,
    "FrameFractionAccuracy": 0.9760127,
    "LeftHandPersistence": 0.992391646,
    "RightHandPersistence": 1.0,
    "RecognizeToPressTimeLeftHand": 3.67776,
    "RecognizeToPressTimeRightHand": 3.011022,
    "LeftThumbAccuracy": 0.9978701,
    "LeftIndexAccuracy": 0.9011329,
    "LeftMiddleAccuracy": 1.0,
    "LeftRingAccuracy": 0.866492152,
    "LeftPinkyAccuracy": 0.9268293,
    "RightThumbAccuracy": 0.996055245,
    "RightIndexAccuracy": 1.0,
    "RightMiddleAccuracy": 1.0,
    "RightRingAccuracy": 0.973544955,
    "RightPinkyAccuracy": 0.9962359,
    "OctaveLeftAccuracy": -1.0,
    "OctaveMiddleLeftAccuracy": 0.9310598,
    "OctaveMiddleRightAccuracy": 0.9965529,
    "OctaveRightAccuracy": 1.0,
    "FingerWidthMultiplier": 1.0,
    "TopMask": 0.39,
    "BottomMask": 0.2,
    "LeftMask": 0.2,
    "RightMask": 0.2,
    "LightingAverage": 0.0302766729,
    "LightingContrast": 0.00733824447,
    "LightingScore": 0.9997512,
    "WorstFrameAccuracyScore": 0.937417865,
    "WorstFrameAccuracyStart": 25.6,
    "WorstFrameAccuracyEnd": 40.8,
    "WorstFrameAccuracyDuration": 15.2,
    "CameraFPS": 89.96872,
    "UnityFPS": 60.00618,
    "TestAppVersion": "0.2",
    "TrackingServiceVersion": "5.17.1",
    "TrackingModelVersion": "N/A",
    "InitThreshold": -1.0,
    "KillThreshold": -1.0,
    "TrackingProviderName": "Screentop Service Provider",
    "TrackingUsesInterpolation": false,
    "TestedAt": "20231214_122133"
  }
]
